setup.py
blogrunner/__init__.py
blogrunner.egg-info/PKG-INFO
blogrunner.egg-info/SOURCES.txt
blogrunner.egg-info/dependency_links.txt
blogrunner.egg-info/requires.txt
blogrunner.egg-info/top_level.txt
blogrunner/AI/KNN.py
blogrunner/AI/__init__.py
blogrunner/AI/get_grade.py
blogrunner/Bottle/__init__.py
blogrunner/Bottle/main.py
blogrunner/CSDN/__init__.py
blogrunner/CSDN/analyse.py
blogrunner/CSDN/keyword.py
blogrunner/CSDN/website.py
blogrunner/MYSQL/__init__.py
blogrunner/MYSQL/sql.py
blogrunner/dist/__init__.py