Metadata-Version: 1.0
Name: blogrunner
Version: 1.1
Summary: This module create the platform for the Linuxer
Home-page: https://github.com/gmftbyGMFTBY
Author: GMFTBY
Author-email: 18811371908@163.com
License: UNKNOWN
Platform: UNKNOWN
